explodingham/__init__.py
explodingham/models/__init__.py
explodingham/models/baseline_models/__init__.py
explodingham/models/baseline_models/regex.py
explodingham/models/compression_learning/__init__.py
explodingham/models/compression_learning/knn.py
explodingham/utils/__init__.py
explodingham/utils/base/__init__.py
explodingham/utils/base/base_classifier.py
explodingham/utils/distance_metrics/__init__.py
explodingham/utils/distance_metrics/ncd.py
explodingham-0.0.4.dist-info/licenses/LICENSE
explodingham-0.0.4.dist-info/METADATA
explodingham-0.0.4.dist-info/WHEEL
explodingham-0.0.4.dist-info/top_level.txt
explodingham-0.0.4.dist-info/RECORD
