Metadata-Version: 2.4
Name: explodingham
Version: 0.0.4
Summary: Oddball machine learning algorithms
Author-email: Peter Jachim <pjachim@outlook.com>
License-Expression: Apache-2.0
Project-URL: Homepage, https://github.com/pjachim/ExplodingHam
Project-URL: Issues, https://github.com/pjachim/ExplodingHam/issues
Classifier: Programming Language :: Python :: 3
Classifier: Operating System :: OS Independent
Requires-Python: >=3.10
License-File: LICENSE
Dynamic: license-file
